MANIFEST.in
README
setup.py
xmi2oerp/__init__.py
xmi2oerp/builder.py
xmi2oerp/model.py
xmi2oerp/uml.py
xmi2oerp/validation.py
xmi2oerp.egg-info/PKG-INFO
xmi2oerp.egg-info/SOURCES.txt
xmi2oerp.egg-info/dependency_links.txt
xmi2oerp.egg-info/requires.txt
xmi2oerp.egg-info/top_level.txt
xmi2oerp/data/OpenObjectStadardElements.xmi
xmi2oerp/data/licenses/agpl3-header.txt
xmi2oerp/data/template/CLASS.py_
xmi2oerp/data/template/README
xmi2oerp/data/template/__init__.py_
xmi2oerp/data/template/__openerp__.py_
xmi2oerp/data/template/data/CLASS_properties.xml
xmi2oerp/data/template/data/CLASS_track.xml
xmi2oerp/data/template/data/README
xmi2oerp/data/template/i18n/README
xmi2oerp/data/template/images/README
xmi2oerp/data/template/report/CLASS.py_
xmi2oerp/data/template/report/CLASS_view.xml
xmi2oerp/data/template/report/README
xmi2oerp/data/template/report/__init__.py_
xmi2oerp/data/template/security/PACKAGE_group.xml
xmi2oerp/data/template/security/README
xmi2oerp/data/template/security/ir.model.access.csv
xmi2oerp/data/template/test/README
xmi2oerp/data/template/view/CLASS_view.xml
xmi2oerp/data/template/view/PACKAGE_menuitem.xml
xmi2oerp/data/template/wizard/CLASS.py_
xmi2oerp/data/template/wizard/CLASS_view.xml
xmi2oerp/data/template/wizard/README
xmi2oerp/data/template/wizard/__init__.py_
xmi2oerp/data/template/workflow/CLASS_workflow.xml
xmi2oerp/scripts/xmi2oerp